image2inchi/__init__.py
image2inchi/config.py
image2inchi/main.py
image2inchi/model.py
image2inchi/model_core.py
image2inchi/preprocess.py
image2inchi/utils.py
Image2InChI-2.0.dist-info/METADATA
Image2InChI-2.0.dist-info/WHEEL
Image2InChI-2.0.dist-info/top_level.txt
Image2InChI-2.0.dist-info/RECORD
