Metadata-Version: 2.1
Name: Image2InChI
Version: 2.0
Summary: Convert a picture to InChI
Author: PanJiaHeng
Author-email: 2905231006@qq.com
License: apache 3.0
Requires-Python: >=3.8
Requires-Dist: torch >=2.1.0
Requires-Dist: numpy ==1.24.3
Requires-Dist: pandas ==2.0.3
Requires-Dist: opencv-python ==4.8.0.76
Requires-Dist: albumentations ==1.3.1
Requires-Dist: timm ==0.9.5
Requires-Dist: tqdm ==4.66.1
Requires-Dist: python-Levenshtein ==0.12.2
Requires-Dist: rdkit ==2023.09.3
Requires-Dist: fairseq ==0.12.2
Requires-Dist: scikit-learn ==1.2.0
